[{"id":0,"name":"Makedonsko Devojce"},{"id":1,"name":"Kad samc dečak bio"},{"id":2,"name":"Ko se sa nama druži"},{"id":3,"name":"Kafanac"},{"id":4,"name":"Ej Branka Branka"},{"id":5,"name":"Skitnice(kad sam decak bio)"},{"id":6,"name":"Vidovdan"},{"id":7,"name":"Janjicar"},{"id":8,"name":"Kaludjeru moj! No un"},{"id":9,"name":"Fijakeri"},{"id":10,"name":"Mile Kitic - Vuk Samotnjak"},{"id":11,"name":"Sve cu dati kucu konje"},{"id":12,"name":"Saban Saulic - To je zena koju volim ja"},{"id":13,"name":"Cveta"},{"id":14,"name":"Zena u crnom sede kraj mene"},{"id":15,"name":"Boban Zdravkovic - Ne dolazi"},{"id":16,"name":"Moj dilbere (sto te volim, ah sto te ljubim)"},{"id":17,"name":"Dva dobra druga, dva prijatelja (u maloj krcmi, i uz casu rujnog vina..)"},{"id":18,"name":"Sinoc sam pola kafane popio"},{"id":19,"name":"Merak mi je"},{"id":20,"name":"Nije mene duso ubilo vino crveno"},{"id":21,"name":"A ja sam negde rujno vino pio"},{"id":22,"name":"Avlije, avlije"},{"id":23,"name":"Zena udata"},{"id":24,"name":"Hvala ti za ljubav"},{"id":25,"name":"Lepa do bola"},{"id":26,"name":"Oprastamtim ti zlatiborske zore"},{"id":27,"name":"Losa navika (hej da nisi tako lepa)"},{"id":28,"name":"Slike u oku (dovoljno je to da mi kazes ti, da i brx tebe ne mogu ziveti)"},{"id":29,"name":"Kosava (ne mogu da te ne volim, ne volim i da bez tebe zivim)"},{"id":30,"name":"Oluja (hajde dodji sve ti prastam)"},{"id":31,"name":"Koktel ljubavi (oo, ona i ja, oo)"},{"id":32,"name":"Od boga si stvorena (koliko sam saml zena poljubio)"},{"id":33,"name":"Potopicu ovaj splav"},{"id":34,"name":"Lela Vranjanka (pusto, pusto, pusto mi je sveee. Nema nema)"},{"id":35,"name":"Pukni zoro (da li cujes mila, moga konja kas)"},{"id":36,"name":"Ruzo rumena"},{"id":37,"name":"Stanite dani, stanite noci (stanite godine)"},{"id":38,"name":"Zanela me svetla"},{"id":39,"name":"Hocu da se zenim dok sam joste mlad"},{"id":40,"name":"Mito bekrijo"},{"id":41,"name":"Crne kose (mozes reci da je svemu kraj nikada ti vjerovala ne bih)"},{"id":42,"name":"Nista banja topla voda"},{"id":43,"name":"Da zakopcam jelece"},{"id":44,"name":"Polomicu case od kristala"},{"id":45,"name":"Jos te nesto cini izuzetnom"},{"id":46,"name":"Nesanica (ivkova slava)"},{"id":47,"name":"Splavovi (ne budite mene, mamuran sam ja)"},{"id":48,"name":"Evo meni moga bekrije"},{"id":49,"name":"Ej samo da mi je..."},{"id":50,"name":"Kunem te strance, jadan nebio"},{"id":51,"name":"Jos te nesto cini izuzetnom"},{"id":52,"name":"Ne udaj se Rado, ne udaj se duso"},{"id":53,"name":"Navikli ste da vam pevam pesme tuzne"},{"id":54,"name":"Pokosovski ciklus"},{"id":55,"name":"Ne žuri se tebi ne putuje"},{"id":56,"name":"Moji stari drugovi"},{"id":57,"name":"Gore more tope se planine"},{"id":58,"name":"Crven cvete"},{"id":59,"name":"Ni jedne usne se ne ljube same"},{"id":60,"name":"A nekad je dolazila stalno"},{"id":61,"name":"Ginem ginem da ti skinem"},{"id":62,"name":"Dance svileno maramce"},{"id":63,"name":"Idem preko zemlje srbije"},{"id":64,"name":"99 žena da me vole"},{"id":65,"name":"Džej Ej malena malena srce si mi zavela"},{"id":66,"name":"Ajde Jano ajde duso"},{"id":67,"name":"Pusti me, sama kad ostaneš videćeš kako je"},{"id":68,"name":"Evo banke cigane moj"},{"id":69,"name":"Luckasta si ti takav sam i ja"},{"id":70,"name":"Djavolu bi dušu dao za merak"},{"id":71,"name":"Prazna casa na mom stolu"},{"id":72,"name":"Lepa je ko san ime joj ne znam"},{"id":73,"name":"Džej, sve se loše nešto nešto"},{"id":74,"name":"Sto imala zelju Stamena"},{"id":75,"name":"Ne rodilo ni njivo ni sljivo"},{"id":76,"name":"Dva galeba dve berige"},{"id":77,"name":"Zapeva sojka ptica (sto se udajases, aman, aman, sto se udajes)"},{"id":78,"name":"Cerge (ostala je samo prazna casa)"},{"id":79,"name":"Nije zivot jedna zena"},{"id":80,"name":"Udade se jagodo"},{"id":81,"name":"Vracam se u bosnu"},{"id":82,"name":"Tiho noci moje zlato spavo"},{"id":83,"name":"Nek mirisu jorgovani"},{"id":84,"name":"Kosava ne mogu da te ne volim"},{"id":85,"name":"Donesi vina krcmarice (daj da pijem tugu da ubijem)"},{"id":86,"name":"Nika nika Marika, koda (makedonska prelepa marija...)"},{"id":87,"name":"Mostovi na moraci (vi spajate rastavljene)"},{"id":88,"name":"Kada bi me pitali ( ejj s tobom bih, nocu zvezde brojala)"},{"id":89,"name":"Ivanova korita"},{"id":90,"name":"Poznao bih te medj hiljadu zena"},{"id":91,"name":"Imala sam ljubav jednu"},{"id":92,"name":"Otvori mi belo lenche"},{"id":93,"name":"Ja ne znam gdje je ona"},{"id":94,"name":"Ne kunite crne oci"},{"id":95,"name":"Nije mene duso ubilo vino rumeno"},{"id":96,"name":"Zvezda scera mesecaa"},{"id":97,"name":"Skitnica"},{"id":98,"name":"Maljčiki"},{"id":99,"name":"Evo banke cigane moj"},{"id":100,"name":"Pamtim jos, one livade one reke"},{"id":101,"name":"Ja ne znam gdje je, s kim noci deli. Meho Puzic"},{"id":102,"name":"Pusti me haris dzin"},{"id":103,"name":"Mali mrav"},{"id":104,"name":"Ne pitaj. Legende"},{"id":105,"name":"Voljela sam voljela, voljela sam ga"},{"id":106,"name":"Dunjo moja"},{"id":107,"name":"Crven fesic u dragoga"},{"id":108,"name":"Usnila je dubak sanak sa Kosova Rada"},{"id":109,"name":"Rastao sam pored dunava"},{"id":110,"name":"Ja jos spavam po navici"},{"id":111,"name":"Ej seki seki"},{"id":112,"name":"Put me zove"},{"id":113,"name":"Imao, imao sam (sada imam jednu gorku uspomenu, i ranu staru)"},{"id":114,"name":"Oj jarane jarane, jarani smo mi"},{"id":115,"name":"Malo ja malo ti - aj neka neka nek se zna, da te volim ja"},{"id":116,"name":"Ruse kose curo imas-zalis li gi ti"},{"id":117,"name":"Aj veseli se kucni domacine"},{"id":118,"name":"Leno leno magdaleno"},{"id":119,"name":"Ti za ljubav nisi rodjena"},{"id":120,"name":"Danima te cekam (Saban Saulic)"},{"id":121,"name":"Ti rumena ruzo kazi majci sta te boli duso"},{"id":122,"name":"Lido Lidija"},{"id":124,"name":"Placite samnom jesenje kise"},{"id":125,"name":"Ja sam ti stari putnik zalutali"},{"id":126,"name":"Puce puska"}]